utils_tool/__init__.py
utils_tool/content.py
utils_tool/file.py
utils_tool/log.py
utils_tool/manager.py
utils_tool/re.py
utils_tool/test_func.py
utils_tool-0.1.5.dist-info/METADATA
utils_tool-0.1.5.dist-info/WHEEL
utils_tool-0.1.5.dist-info/top_level.txt
utils_tool-0.1.5.dist-info/RECORD
